main.py
wei516_enconly-0.2.3.dist-info/METADATA
wei516_enconly-0.2.3.dist-info/WHEEL
wei516_enconly-0.2.3.dist-info/entry_points.txt
wei516_enconly-0.2.3.dist-info/top_level.txt
wei516_enconly-0.2.3.dist-info/RECORD
