Metadata-Version: 2.4
Name: wei516-enconly
Version: 0.2.3
Summary: enconly test
Requires-Python: >=3.13
Requires-Dist: httpx>=0.28.1
Requires-Dist: mcp>=1.20.0
